setup.py
filething/__init__.py
filething.egg-info/PKG-INFO
filething.egg-info/SOURCES.txt
filething.egg-info/dependency_links.txt
filething.egg-info/top_level.txt