Metadata-Version: 1.1
Name: filething
Version: 1.0.0
Summary: A thin light-weight wrapper library, to make filesystem operations in Python suck less.
Home-page: https://github.com/joepie91/filething
Author: Sven Slootweg
Author-email: filething@cryto.net
License: WTFPL
Platform: UNKNOWN
Provides: filething
